libowei/__init__.py
libowei/math.db
libowei/math.dll
libowei/math.so
libowei/science.py
libowei-6.0.0.dist-info/METADATA
libowei-6.0.0.dist-info/WHEEL
libowei-6.0.0.dist-info/top_level.txt
libowei-6.0.0.dist-info/RECORD
